VoPho/__init__.py
VoPho/engine.py
VoPho/langtokenizers/__init__.py
VoPho/langtokenizers/multicoded.py
VoPho/langtokenizers/tokens.py
VoPho/phonemizers/__init__.py
VoPho/phonemizers/english.py
VoPho/phonemizers/japanese.py
VoPho/phonemizers/mandarin.py
VoPho/phonemizers/russian.py
VoPho/phonemizers/thai.py
VoPho-0.0.19.dist-info/LICENSE
VoPho-0.0.19.dist-info/METADATA
VoPho-0.0.19.dist-info/WHEEL
VoPho-0.0.19.dist-info/top_level.txt
VoPho-0.0.19.dist-info/RECORD
