Metadata-Version: 2.2
Name: VoPho
Version: 0.0.19
Summary: An easy to use Multilingual phonemization meta-library
Author: ShoukanLabs.
Project-URL: homepage, https://github.com/ShoukanLabs/VoPho
Keywords: Phonemization,TTS,Multilingual
Classifier: Programming Language :: Python :: 3
Classifier: License :: OSI Approved :: MIT License
Classifier: Operating System :: OS Independent
Requires-Python: >=3.6
License-File: LICENSE
Requires-Dist: epitran
Requires-Dist: ruphon
Requires-Dist: ruaccent==1.5.8
Requires-Dist: cn2an==0.5.22
Requires-Dist: colorama==0.4.6
Requires-Dist: termcolor==2.4.0
Requires-Dist: openphonemizer==0.1.2
Requires-Dist: unidic-lite==1.0.8
Requires-Dist: mecab-python3==1.0.9
Requires-Dist: cutlet==0.4.0
Requires-Dist: jieba==0.42.1
Requires-Dist: pypinyin==0.52.0
Requires-Dist: pythainlp==5.0.4
Requires-Dist: torch>=2.0.0
Requires-Dist: langdetect==1.0.9
Requires-Dist: lingua-language-detector==2.0.2
Requires-Dist: pywsd==1.2.5
Requires-Dist: sentence-transformers
Requires-Dist: scikit-learn
Requires-Dist: misaki[en]>=0.5.6
